MANIFEST.in
README.md
VERSION
setup.py
data_geo/__init__.py
data_geo/geojson.py
data_geo.egg-info/PKG-INFO
data_geo.egg-info/SOURCES.txt
data_geo.egg-info/dependency_links.txt
data_geo.egg-info/not-zip-safe
data_geo.egg-info/requires.txt
data_geo.egg-info/top_level.txt