Metadata-Version: 2.1
Name: data-geo
Version: 0.1.2
Summary: DataDBS for geojson
Home-page: https://gitlab.com/pineiden/datadbs-geojson
Author: David Pineda Osorio
Author-email: dpineda@csn.uchile.cl
License: GPLv3
